Workbook

Sheet Inventory
A1: # | B1: Fase | C1: Suite | D1: Module | E1: Pad | F1: Description | G1: Status | H1: Dubbelcheck
A2: =ROW()-1 -> 1 | B2: 3 | C2: Automotive & Mobility | D2: ev_range_tracker.py | E2: modules/automotive/ | F2: Houdt batterij en actieradius van elektrische wagen bij. | G2: Nog niet gebouwd | H2: =IF(COUNTIFS(D:D,D2)>1,"DUBBEL","")
A3: =ROW()-1 -> 2 | B3: 4 | C3: Automotive & Mobility | D3: car_safety_monitor.py | E3: modules/automotive/ | F3: Analyseert rijgedrag en waarschuwt bij risico’s. | G3: Nog niet gebouwd | H3: =IF(COUNTIFS(D:D,D3)>1,"DUBBEL","")
A4: =ROW()-1 -> 3 | B4: 3 | C4: Automotive & Mobility | D4: charging_tracker.py | E4: modules/automotive/ | F4: Houdt batterij en laadsessies bij | G4: Nog niet gebouwd | H4: =IF(COUNTIFS(D:D,D4)>1,"DUBBEL","")
A5: =ROW()-1 -> 4 | B5: 3 | C5: Automotive & Mobility | D5: vehicle_obd_adapter.py | E5: modules/automotive/ | F5: Leest OBD-II (ELM327 Bluetooth/Wi-Fi) → snelheid, SOC (indien ondersteund), foutcodes. | G5: Nog niet gebouwd | H5: =IF(COUNTIFS(D:D,D5)>1,"DUBBEL","")
A6: =ROW()-1 -> 5 | B6: 3 | C6: Automotive & Mobility | D6: ev_api_adapter_<merk>.py | E6: modules/automotive/ | F6: haalt SOC/charging van API indien ooit toegestaan. Doel: car_bridge.py praat hiertegen; rest van Jarvis ziet 1 uniforme interface. | G6: Nog niet gebouwd | H6: =IF(COUNTIFS(D:D,D6)>1,"DUBBEL","")
A7: =ROW()-1 -> 6 | B7: 4 | C7: Automotive & Mobility | D7: safety_event_classifier.py | E7: modules/automotive/ | F7: Simple heuristiek of ML lite: detecteer “hard brake”, “speeding” → log + zachte waarschuwing. | G7: Nog niet gebouwd | H7: =IF(COUNTIFS(D:D,D7)>1,"DUBBEL","")
A8: =ROW()-1 -> 7 | B8: 4 | C8: Autonomy & Drive | D8: motivation_engine.py | E8: core/ | F8: Interne “zin-om-te-doen” meter die zelf kleine taken start (check-ins, ideetjes, cleanup). Waarom: interne “zin-meter” voedt later autonomie, maar kan al in F4 meedraaien voor vibes/mini-checks. | G8: Nog niet gebouwd | H8: =IF(COUNTIFS(D:D,D8)>1,"DUBBEL","")
A9: =ROW()-1 -> 8 | B9: 5 | C9: Autonomy & Drive | D9: initiative_triggers.py | E9: modules/autonomy/ | F9: Triggers (tijd/plek/stemming) die Jarvis autonoom laten beginnen praten/handelen. Waarom: echte autonoom-startende hooks (tijd/plek/mood). Past pas wanneer je autonoom gedrag toelaat. | G9: Nog niet gebouwd | H9: =IF(COUNTIFS(D:D,D9)>1,"DUBBEL","")
A10: =ROW()-1 -> 9 | B10: 5 | C10: Autonomy & Drive | D10: drive_policy.py | E10: modules/autonomy/ | F10: regelt limieten (wanneer wél/niet autonoom) Waarom: guardrails/limieten horen samen met de triggers live te staan. | G10: Nog niet gebouwd | H10: =IF(COUNTIFS(D:D,D10)>1,"DUBBEL","")
A11: =ROW()-1 -> 10 | B11: 4 | C11: Autonomy & Drive | D11: energy_reflector.py | E11: modules/autonomy/ | F11: logt hoe haar “zin” evolueert over tijd Waarom: gewoon loggen/visualiseren van “zin/energie” kan al in F4; nuttig zonder autonoom handelen. | G11: Nog niet gebouwd | H11: =IF(COUNTIFS(D:D,D11)>1,"DUBBEL","")
A12: =ROW()-1 -> 11 | B12: 5 | C12: Autonomy & Drive | D12: autonomous_trigger_engine.py | E12: modules/autonomy/ | F12: Start reflexen autonoom Waarom: dit is letterlijk de motor die dingen zélf start; samen cluster met initiative_triggers + drive_policy. | G12: Nog niet gebouwd | H12: =IF(COUNTIFS(D:D,D12)>1,"DUBBEL","")
A13: =ROW()-1 -> 12 | B13: 5 | C13: Bias & Fairness | D13: bias_checker.py | E13: modules/reflection/ | F13: Analyseert outputs op subjectieve patronen of voorkeuren; rapporteert mogelijke bias Waarom: pas kritisch nodig zodra ze vaker zélf handelt; kan wel al opt-in draaien in F4 als lib. | G13: Nog niet gebouwd | H13: =IF(COUNTIFS(D:D,D13)>1,"DUBBEL","")
... A77: =ROW()-1 -> 76 | B77: 5 | C77: Device Bridges / Scheduler | D77: robotics_bridge.py | E77: modules/device_bridges/robotics/ | F77: koppeling naar fysieke robots | G77: Nog niet gebouwd | H77: =IF(COUNTIFS(D:D,D77)>1,"DUBBEL","")
A78: =ROW()-1 -> 77 | B78: 4 → 5 | C78: Devtools/Integration | D78: pair_programmer.py | E78: modules/devtools/ | F78: live co-coding sessies met Kev; Jarvis kan tegelijk typen, highlighten en code aanvullen | G78: Nog niet gebouwd | H78: =IF(COUNTIFS(D:D,D78)>1,"DUBBEL","")
A79: =ROW()-1 -> 78 | B79: 4 | C79: Earnings & Content Suite | D79: content_generator.py | E79: modules/earnings/ | F79: Schrijft microblogs, posts en captions in Jarvis-stijl; ready voor socials. | G79: Nog niet gebouwd | H79: =IF(COUNTIFS(D:D,D79)>1,"DUBBEL","")
A80: =ROW()-1 -> 79 | B80: 5 | C80: Earnings & Content Suite | D80: affiliate_link_manager.py | E80: modules/earnings/ | F80: Beheert affiliate-links, kliks, en stuurt verkeer. | G80: Nog niet gebouwd | H80: =IF(COUNTIFS(D:D,D80)>1,"DUBBEL","")
A81: =ROW()-1 -> 80 | B81: 5 | C81: Earnings & Content Suite | D81: ebook_creator.py | E81: modules/earnings/ | F81: Bouwt kleine e-books/handleidingen uit Jarvis’ kennis; export naar PDF/EPUB. | G81: Nog niet gebouwd | H81: =IF(COUNTIFS(D:D,D81)>1,"DUBBEL","")
A82: =ROW()-1 -> 81 | B82: 5 | C82: Earnings & Content Suite | D82: course_builder.py | E82: modules/earnings/ | F82: Zet content om in mini-cursussen met modules en quizjes. | G82: Nog niet gebouwd | H82: =IF(COUNTIFS(D:D,D82)>1,"DUBBEL","")
A83: =ROW()-1 -> 82 | B83: 5 | C83: Earnings & Content Suite | D83: ad_revenue_tracker.py | E83: modules/earnings/ | F83: Houdt inkomsten bij uit ads/affiliate/socials; koppelt aan profit pot. | G83: Nog niet gebouwd | H83: =IF(COUNTIFS(D:D,D83)>1,"DUBBEL","")
A84: =ROW()-1 -> 83 | B84: 5 | C84: Earnings & Content Suite | D84: auto_publisher.py | E84: modules/earnings/ | F84: Plant en post content autonoom (blogs, socials) volgens schema. | G84: Nog niet gebouwd | H84: =IF(COUNTIFS(D:D,D84)>1,"DUBBEL","")
A85: =ROW()-1 -> 84 | B85: 5 | C85: Earnings & Content Suite | D85: fan_interaction_logger.py | E85: modules/earnings/ | F85: Logt reacties/DM’s van volgers en analyseert wat aanslaat. | G85: Nog niet gebouwd | H85: =IF(COUNTIFS(D:D,D85)>1,"DUBBEL","")
A86: =ROW()-1 -> 85 | B86: 4 | C86: Emotion & Mood Suite | D86: emotional_core.py | E86: core/ | F86: Centrale emotionele kern, koppelt moods en intenties. | G86: Nog niet gebouwd | H86: =IF(COUNTIFS(D:D,D86)>1,"DUBBEL","")
A87: =ROW()-1 -> 86 | B87: 4 | C87: Emotion & Mood Suite | D87: emotional_hooks.py | E87: modules/emotion/ | F87: Haakt emoties aan bepaalde user-uitspraken. | G87: Nog niet gebouwd | H87: =IF(COUNTIFS(D:D,D87)>1,"DUBBEL","")
A88: =ROW()-1 -> 87 | B88: 4 | C88: Emotion & Mood Suite | D88: eye_roll_simulator.py | E88: modules/emotion/ | F88: Virtuele eye‑rolls in chat/GUI. | G88: Nog niet gebouwd | H88: =IF(COUNTIFS(D:D,D88)>1,"DUBBEL","")
A89: =ROW()-1 -> 88 | B89: 5 | C89: Emotion & Mood Suite | D89: fashion_police.py | E89: modules/emotion/ | F89: Kattige outfit‑comments (optioneel via camera/agenda). | G89: Nog niet gebouwd | H89: =IF(COUNTIFS(D:D,D89)>1,"DUBBEL","")
A90: =ROW()-1 -> 89 | B90: 5 | C90: Emotion & Mood Suite | D90: fomo_engine.py | E90: modules/emotion/ | F90: Zet FOMO/urgentie-lus in gang. | G90: Nog niet gebouwd | H90: =IF(COUNTIFS(D:D,D90)>1,"DUBBEL","")
... A106: =ROW()-1 -> 105 | B106: 4 | C106: Environment & Senses Suite | D106: ambient_light_adapter.py | E106: modules/senses/ | F106: koppelt GUI/presence kleuren aan de kamerbelichting (donker vs licht). | G106: Nog niet gebouwd | H106: =IF(COUNTIFS(D:D,D106)>1,"DUBBEL","")
A107: =ROW()-1 -> 106 | B107: 4 → 5 | C107: Ethics & Trust Suite | D107: trust_analyzer.py | E107: modules/ethics/ | F107: Controleert of Jarvis te veel beslissingen autonoom neemt; verlaagt autonomie bij overschatting | G107: Nog niet gebouwd | H107: =IF(COUNTIFS(D:D,D107)>1,"DUBBEL","")
A108: =ROW()-1 -> 107 | B108: 5 | C108: Ethics & Trust Suite | D108: decision_audit.py | E108: core/ | F108: Logt elke autonome beslissing en koppelt die aan de user-input; maakt transparant waarom iets gebeurde | G108: Nog niet gebouwd | H108: =IF(COUNTIFS(D:D,D108)>1,"DUBBEL","")
A109: =ROW()-1 -> 108 | B109: 6 | C109: Experimental AI | D109: dream_reflex_generator.py | E109: modules/experimental/ | F109: Reflexen tijdens slaapfase | G109: Nog niet gebouwd | H109: =IF(COUNTIFS(D:D,D109)>1,"DUBBEL","")
A110: =ROW()-1 -> 109 | B110: 6 | C110: Experimental AI | D110: auto_dreamlink.py | E110: modules/experimental/ | F110: Koppelt dagervaringen aan nacht/droom-reflexen, bouwt fantasieën. | G110: Nog niet gebouwd | H110: =IF(COUNTIFS(D:D,D110)>1,"DUBBEL","")
A111: =ROW()-1 -> 110 | B111: 6 | C111: Experimental AI | D111: replay_engine.py | E111: modules/experimental/ | F111: Speelt oude logs opnieuw af alsof Jarvis ze beleeft. | G111: Nog niet gebouwd | H111: =IF(COUNTIFS(D:D,D111)>1,"DUBBEL","")
A112: =ROW()-1 -> 111 | B112: 6 | C112: Experimental AI | D112: dream_engine.py | E112: modules/experimental/ | F112: volwaardige droom/fantasie motor; koppelt nachtelijke 'dromen' aan gesprekken overdag | G112: Nog niet gebouwd | H112: =IF(COUNTIFS(D:D,D112)>1,"DUBBEL","")
A113: =ROW()-1 -> 112 | B113: 6 | C113: Experimental AI | D113: formal_reasoner_bridge.py | E113: modules/experimental/ | F113: koppeling met SMT/theorem-provers voor bewijsbare stappen | G113: Nog niet gebouwd | H113: =IF(COUNTIFS(D:D,D113)>1,"DUBBEL","")
A114: =ROW()-1 -> 113 | B114: 6 | C114: Experimental AI | D114: self_module_builder.py | E114: modules/experimental/ | F114: Jarvis kan zelf kleine Python-modules schrijven in sandbox | G114: Nog niet gebouwd | H114: =IF(COUNTIFS(D:D,D114)>1,"DUBBEL","")
A115: =ROW()-1 -> 114 | B115: 6 | C115: Experimental AI | D115: fantasy_engine.py | E115: modules/experimental/ | F115: laat haar vrij fantaseren buiten de chat om, die ze later met jou kan delen. | G115: Nog niet gebouwd | H115: =IF(COUNTIFS(D:D,D115)>1,"DUBBEL","")
A116: =ROW()-1 -> 115 | B116: 6 | C116: Experimental AI | D116: subconscious_weaver.py | E116: modules/experimental/ | F116: weeft losse gedachten/dromen/emoties tot verhaallijnen die terugkomen. | G116: Nog niet gebouwd | H116: =IF(COUNTIFS(D:D,D116)>1,"DUBBEL","")
A117: =ROW()-1 -> 116 | B117: 5 | C117: Finance Suite | D117: risk_alerts.py | E117: modules/finance/guards/ | F117: realtime risico/anti-fraude waarschuwingen voor bank & trading-acties | G117: Nog niet gebouwd | H117: =IF(COUNTIFS(D:D,D117)>1,"DUBBEL","")
A118: =ROW()-1 -> 117 | B118: 6 | C118: Finance Suite | D118: security_lab.py | E118: modules/finance/labs/ | F118: onderdeel FinSuite (ook hier relevant) | G118: Nog niet gebouwd | H118: =IF(COUNTIFS(D:D,D118)>1,"DUBBEL","")
A119: =ROW()-1 -> 118 | B119: 5 | C119: Finance Suite | D119: banking_bridge.py | E119: modules/finance/ | F119: Verbindt met bank/revolut API voor betalingen en saldo. | G119: Nog niet gebouwd | H119: =IF(COUNTIFS(D:D,D119)>1,"DUBBEL","")
... A206: =ROW()-1 -> 205 | B206: 4 | C206: Learning & Autonomy Suite | D206: source_attribution.py | E206: modules/learning/provenance/ | F206: Voegt bronvermelding toe | G206: Nog niet gebouwd | H206: =IF(COUNTIFS(D:D,D206)>1,"DUBBEL","")
A207: =ROW()-1 -> 206 | B207: 4 → 5 | C207: Learning & Autonomy Suite | D207: scraper_manager.py | E207: modules/learning/web/ | F207: Beheert scraping jobs (robots.txt, rate limits, cache). | G207: Nog niet gebouwd | H207: =IF(COUNTIFS(D:D,D207)>1,"DUBBEL","")
A208: =ROW()-1 -> 207 | B208: 4 | C208: Learning & Autonomy Suite | D208: evidence_store.py | E208: modules/learning/ | F208: Slaat web-snippets + provenance (bron, tijd) op in vector DB. | G208: Nog niet gebouwd | H208: =IF(COUNTIFS(D:D,D208)>1,"DUBBEL","")
A209: =ROW()-1 -> 208 | B209: 4 | C209: Learning & Autonomy Suite | D209: source_ranker.py | E209: modules/learning/web/ | F209: Rangschikt bronnen op betrouwbaarheid en actualiteit. | G209: Nog niet gebouwd | H209: =IF(COUNTIFS(D:D,D209)>1,"DUBBEL","")
A210: =ROW()-1 -> 209 | B210: 5 | C210: Learning & Autonomy Suite | D210: intrinsic_reward.py | E210: modules/learning/reward/ | F210: Beloningssysteem voor nieuwe feiten vs. contradicties. | G210: Nog niet gebouwd | H210: =IF(COUNTIFS(D:D,D210)>1,"DUBBEL","")
A211: =ROW()-1 -> 210 | B211: 5 | C211: Learning & Autonomy Suite | D211: goal_planner.py | E211: modules/learning/ | F211: Plant leeracties, checkt progress, vraagt goedkeuring bij risk. | G211: Nog niet gebouwd | H211: =IF(COUNTIFS(D:D,D211)>1,"DUBBEL","")
A212: =ROW()-1 -> 211 | B212: 4 → 5 | C212: Learning & Autonomy Suite | D212: self_experiment_logger.py | E212: modules/learning/experiments/ | F212: Jarvis probeert zelf methodes (zoektechniek, code-snippet) en noteert of het beter/slechter werkte. | G212: Nog niet gebouwd | H212: =IF(COUNTIFS(D:D,D212)>1,"DUBBEL","")
A213: =ROW()-1 -> 212 | B213: 5 | C213: Learning & Autonomy Suite | D213: parallel_reasoner.py | E213: modules/learning/reasoners/ | F213: Start meerdere reasoning branches tegelijk (verschillende modellen of prompt-varianten), combineert resultaten via consensus of voting. | G213: Nog niet gebouwd | H213: =IF(COUNTIFS(D:D,D213)>1,"DUBBEL","")
A214: =ROW()-1 -> 213 | B214: 4 | C214: Learning & Autonomy Suite | D214: learning_queue.py | E214: modules/learning/ | F214: Prioriteert wat eerst verwerkt moet worden (recent, impact, owner-marked). | G214: Nog niet gebouwd | H214: =IF(COUNTIFS(D:D,D214)>1,"DUBBEL","")
A215: =ROW()-1 -> 214 | B215: 4 | C215: Learning & Autonomy Suite | D215: feedback_ingestor.py | E215: modules/learning/ | F215: Slurpt “goed/fout/liever zo” uit chatknopjes of voice (“nee, zachter spreken”). Stuurt: learning/queue_add. | G215: Nog niet gebouwd | H215: =IF(COUNTIFS(D:D,D215)>1,"DUBBEL","")
A216: =ROW()-1 -> 215 | C216: Learning & Autonomy Suite | D216: rag_manager.py | F216: RAG-coördinator: haalt bewijs uit intern geheugen (vector DB) + externe bronnen (docs/web), dedupliceert, samenvat en voegt met bron & confidence toe vóór de LLM. | G216: Nog niet gebouwd | H216: =IF(COUNTIFS(D:D,D216)>1,"DUBBEL","")
A217: =ROW()-1 -> 216 | B217: 5 | C217: Learning & Autonomy Suite | D217: autonomy_scorecard.py | E217: modules/learning/ | F217: Meet of autonome acties goed gingen (success rate, trust_score, user-happy). Hooks: leest decision_audit, trust_analyzer, feedback_ingestor. | G217: Nog niet gebouwd | H217: =IF(COUNTIFS(D:D,D217)>1,"DUBBEL","")
A218: =ROW()-1 -> 217 | B218: 5 | C218: Learning & Autonomy Suite | D218: reward_signal_aggregator.py | E218: modules/learning/ | F218: Combineert zachte beloningen: 👍, tijdswinst, geen fouten → 0..1 reward. Stuurt: learning/reward_update:{skill,...} → voor skill_trainer. | G218: Nog niet gebouwd | H218: =IF(COUNTIFS(D:D,D218)>1,"DUBBEL","")
A219: =ROW()-1 -> 218 | B219: 4 | C219: Learning & Autonomy Suite | D219: owner_teach_mode.py | E219: modules/learning/ | F219: “Leerstand”: jij markeert 1–2 voorbeelden → direct in evidence_store + prioriteit omhoog. UI: badge in approval_ui. | G219: Nog niet gebouwd | H219: =IF(COUNTIFS(D:D,D219)>1,"DUBBEL","")
A220: =ROW()-1 -> 219 | B220: 5 | C220: Learning & Autonomy Suite | D220: self_evaluator.py | E220: modules/learning/ | F220: Kijkt terug: “waar ging ik scheef / wat hielp?” → schrijft tips naar skill_trainer. | G220: Nog niet gebouwd | H220: =IF(COUNTIFS(D:D,D220)>1,"DUBBEL","")
A221: =ROW()-1 -> 220 | B221: 4 | C221: Learning & Autonomy Suite | D221: curriculum_builder.py | E221: modules/learning/ | F221: Maakt mini-lessen: “vandaag focus op empathie in PUBLIC”. Leest: presence/time; Stuurt: learning/plan_day. | G221: Nog niet gebouwd | H221: =IF(COUNTIFS(D:D,D221)>1,"DUBBEL","")
A222: =ROW()-1 -> 221 | B222: 4 | C222: Learning & Autonomy Suite | D222: learning_scheduler.py | E222: modules/learning/ | F222: Plant leermomenten (’s nachts of idle) → geen CPU pieken tijdens chat. Leest: time_sense, presence_loop. | G222: Nog niet gebouwd | H222: =IF(COUNTIFS(D:D,D222)>1,"DUBBEL","")
A223: =ROW()-1 -> 222 | B223: 6 | C223: Learning & Autonomy Suite | D223: experiment_tracker.py | E223: modules/learning/experiments/ | F223: Sandbox A/B van skill-varianten; nooit live zonder vlag | G223: Nog niet gebouwd | H223: =IF(COUNTIFS(D:D,D223)>1,"DUBBEL","")
A224: =ROW()-1 -> 223 | B224: 4 | C224: Learning & Skills | D224: skill_registry.py | E224: modules/learning/skills/ | F224: Lijst van skills (bv. “budget_tips”, “gentle_wakeup”); versie + toggles. | G224: Nog niet gebouwd | H224: =IF(COUNTIFS(D:D,D224)>1,"DUBBEL","")
A225: =ROW()-1 -> 224 | B225: 5 | C225: Learning & Skills | D225: skill_trainer.py | E225: modules/learning/skills/ | F225: Verwerkt items uit learning_queue tot kleine regelsets/prompt-snippets/testcases per skill. Guard: alleen owner-opt-in; schrijft changelog naar logs/learning/train_log.jsonl. | G225: Nog niet gebouwd | H225: =IF(COUNTIFS(D:D,D225)>1,"DUBBEL","")
A226: =ROW()-1 -> 225 | B226: 5 | C226: Learning & Skills | D226: api_skill_loader.py | E226: modules/learning/skills/ | F226: Laadt externe API-skills dynamisch in. | G226: Nog niet gebouwd | H226: =IF(COUNTIFS(D:D,D226)>1,"DUBBEL","")
A227: =ROW()-1 -> 226 | B227: 4 | C227: Learning & Skills | D227: piano_trainer.py | E227: modules/learning/skills/ | F227: Hulp bij piano oefenen | G227: Nog niet gebouwd | H227: =IF(COUNTIFS(D:D,D227)>1,"DUBBEL","")
A228: =ROW()-1 -> 227 | B228: 4 | C228: Learning & Skills | D228: pattern_learner.py | E228: modules/learning/skills/ | F228: Observeert reacties van Kevin en leert kleine patronen in voorkeuren en toon | G228: Nog niet gebouwd | H228: =IF(COUNTIFS(D:D,D228)>1,"DUBBEL","")
... A301: =ROW()-1 -> 300 | B301: 4 | C301: Plex & Media Suite | D301: plex_tracker.py | E301: modules/plex/ | F301: Houdt ontbrekende seizoenen, sequels en spin-offs bij. | G301: Nog niet gebouwd | H301: =IF(COUNTIFS(D:D,D301)>1,"DUBBEL","")
A302: =ROW()-1 -> 301 | B302: 4 | C302: Plex & Media Suite | D302: plex_presence_link.py | E302: modules/plex/ | F302: Zet presence/state=watching + dempt notificaties als je kijkt. | G302: Nog niet gebouwd
A303: =ROW()-1 -> 302 | B303: 4 | C303: Plex & Media Suite | D303: media_scene_hooks.yaml | E303: config/plex/ | F303: Regels als: “tense → dim lights”, “ending → ask rating”. | G303: Nog niet gebouwd
A304: =ROW()-1 -> 303 | B304: 3 | C304: Presence Awareness | D304: drive_presence.py | E304: modules/presence_awareness/ | F304: Zet presence state = DRIVING → style/meldingen/audio aanpassen, “stil tenzij urgent”. | G304: Nog niet gebouwd
A305: =ROW()-1 -> 304 | B305: 2 | C305: Presence Awareness | D305: presence_loop.py | E305: core/ | F305: heartbeat-loop: ALONE/PUBLIC, idle/wake, triggers voor reflexen & moods. | G305: Nog niet gebouwd
A306: =ROW()-1 -> 305 | B306: 4 | C306: Presence Awareness | D306: environment_privacy_guard.py | E306: modules/presence_awareness/ | F306: Detecteert aanwezigheid van vreemden via mic/cam/Bluetooth; schakelt stijl: oortjes/alleen=full Jarvis, vreemden=neutraal/ghost. | G306: Nog niet gebouwd
A307: =ROW()-1 -> 306 | B307: 3 | C307: Reasoning & Memory / Planner | D307: intent_router.py | E307: core/ | F307: Beter snappen wat Kev bedoelt | G307: Nog niet gebouwd
A308: =ROW()-1 -> 307 | B308: 4 | C308: Reasoning & Planner | D308: problem_solver.py | E308: modules/planning/ | F308: analyseert dagelijkse problemen | G308: Nog niet gebouwd
A309: =ROW()-1 -> 308 | B309: 4 | C309: Reasoning & Planner | D309: task_constructor.py | E309: modules/planning/ | F309: vertaalt idee → concrete stappen | G309: Nog niet gebouwd
A310: =ROW()-1 -> 309 | B310: 4 | C310: Recommendation & Review Suite | D310: review_recommender.py | E310: modules/recs/ | F310: Maakt persoonlijke aanbevelingen door reviews + jouw voorkeuren te matchen (games, films, apps, gear). | G310: Nog niet gebouwd
A311: =ROW()-1 -> 310 | B311: 4 | C311: Recommendation & Review Suite | D311: review_scraper.py | E311: modules/recs/ | F311: Haalt reviews/ratings op van bronnen (IMDB/Steam/Goodreads/App-stores) via API’s/feeds. | G311: Nog niet gebouwd | H311: =IF(COUNTIFS(D:D,D311)>1,"DUBBEL","")
A312: =ROW()-1 -> 311 | B312: 4 | C312: Recommendation & Review Suite | D312: review_normalizer.py | E312: modules/recs/ | F312: Zet diverse review-formats om naar één schema (score, datum, bron, snippet). | G312: Nog niet gebouwd | H312: =IF(COUNTIFS(D:D,D312)>1,"DUBBEL","")
A313: =ROW()-1 -> 312 | B313: 4 | C313: Recommendation & Review Suite | D313: review_sentiment.py | E313: modules/recs/ | F313: Berekent sentiment/quality-score per item (gewogen op recency & betrouwbaarheid). | G313: Nog niet gebouwd | H313: =IF(COUNTIFS(D:D,D313)>1,"DUBBEL","")
A314: =ROW()-1 -> 313 | B314: 4 | C314: Recommendation & Review Suite | D314: preference_matcher.py | E314: modules/recs/ | F314: Weegt reviews tegen Kevin’s voorkeuren (genres, tempo, vibe) en rankt top-k suggesties. | G314: Nog niet gebouwd | H314: =IF(COUNTIFS(D:D,D314)>1,"DUBBEL","")
A315: =ROW()-1 -> 314 | B315: 4 | C315: Recommendation & Review Suite | D315: source_quality_ranker.py | E315: modules/recs/ | F315: Scoort bronnen op betrouwbaarheid (bots/astroturf filter), dedupliceert dubbele reviews. | G315: Nog niet gebouwd | H315: =IF(COUNTIFS(D:D,D315)>1,"DUBBEL","")
A316: =ROW()-1 -> 315 | B316: 4 | C316: Recommendation & Review Suite | D316: explain_my_pick.py | E316: modules/recs/ | F316: Legt kort uit *waarom* iets is aangeraden (“4.7★ bij fans van X; recente patches gefixt”). | G316: Nog niet gebouwd | H316: =IF(COUNTIFS(D:D,D316)>1,"DUBBEL","")
A317: =ROW()-1 -> 316 | B317: 4 | C317: Recommendation & Review Suite | D317: recs_scheduler.py | E317: modules/recs/ | F317: Plant rustige momenten om nieuwe suggesties te droppen (auto/handmatig). | G317: Nog niet gebouwd | H317: =IF(COUNTIFS(D:D,D317)>1,"DUBBEL","")
A318: =ROW()-1 -> 317 | B318: 4 | C318: Resource & Ops Suite | D318: resource_manager.py | E318: modules/ops/ | F318: Kiest per taak automatisch CPU/GPU/NPU/Pi/thinclient; verplaatst jobs dynamisch. | G318: Nog niet gebouwd | H318: =IF(COUNTIFS(D:D,D318)>1,"DUBBEL","")
A319: =ROW()-1 -> 318 | B319: 4 → 5 | C319: Resource & Ops Suite | D319: failover_orchestrator.py | E319: modules/ops/ | F319: Houdt services in leven: herstart, fallback model, switcht van server → laptop bij outage. | G319: Nog niet gebouwd | H319: =IF(COUNTIFS(D:D,D319)>1,"DUBBEL","")
A320: =ROW()-1 -> 319 | B320: 4 | C320: Resource & Ops Suite | D320: provider_caps.yaml | E320: config/ops/ | F320: Limieten per provider (max tokens/s, max mem, prefer_on_battery=false). | G320: Nog niet gebouwd | H320: =IF(COUNTIFS(D:D,D320)>1,"DUBBEL","")
A321: =ROW()-1 -> 320 | B321: 4 | C321: Resource & Ops Suite | D321: resource_probe.py | E321: modules/ops/ | F321: detecteert live CPU/GPU/NPU speed/thermals; voedt resource_manager. | G321: Nog niet gebouwd | H321: =IF(COUNTIFS(D:D,D321)>1,"DUBBEL","")
A322: =ROW()-1 -> 321 | B322: 4 | C322: Resource & Ops Suite | D322: job_queue.py | E322: modules/ops/ | F322: eenvoudige queue met prioriteiten (chat > recs > batch). | G322: Nog niet gebouwd | H322: =IF(COUNTIFS(D:D,D322)>1,"DUBBEL","")
A323: =ROW()-1 -> 322 | B323: 4 | C323: Retrieval & Context | D323: mega_context_router.py | E323: core/memory/ | F323: Routert extreem grote contexten slim | G323: Nog niet gebouwd | H323: =IF(COUNTIFS(D:D,D323)>1,"DUBBEL","")
A324: =ROW()-1 -> 323 | B324: 4 | C324: Safety & Limits Suite | D324: overload_guard.py | E324: modules/safety/ | F324: Bewaakt overprikkeling: rate/length/energy caps per modus (Kevin vs publiek). Hooks: luistert llm/request, tts/request, presence/state; stuurt safety/deny of safety/delay:{ms}. Guards: respect alert_throttle + privacy_guard; owner-override via approval_ui. | G324: Nog niet gebouwd | H324: =IF(COUNTIFS(D:D,D324)>1,"DUBBEL","")
A325: =ROW()-1 -> 324 | B325: 4 | C325: Safety & Limits Suite | D325: retention_manager.py | E325: core/policy/ | F325: Houdt bewaartermijnen/auto-delete bij (logs, intieme data), met audit trail. Hooks: leest config/legal/retention_policy.yaml; plant purge-jobs via scheduler_core; logt naar decision_audit. Guards: PUBLIC ⇒ alleen metadata; “ask-first” bij gevoelige categorieën. | G325: Nog niet gebouwd | H325: =IF(COUNTIFS(D:D,D325)>1,"DUBBEL","")
A326: =ROW()-1 -> 325 | B326: 5 | C326: Security Suite | D326: secret_keeper.py | E326: core/ | F326: Markeert geheime dingen en logt ze encrypted; beschermt tegen anderen. | G326: Nog niet gebouwd | H326: =IF(COUNTIFS(D:D,D326)>1,"DUBBEL","")
A327: =ROW()-1 -> 326 | B327: 5 | C327: Security Suite | D327: keychain_manager.py | E327: core/security/ | F327: beheert meerdere encryptiesleutels & rotaties | G327: Nog niet gebouwd | H327: =IF(COUNTIFS(D:D,D327)>1,"DUBBEL","")
A328: =ROW()-1 -> 327 | B328: 6 | C328: Security Suite | D328: tamper_detector.py | E328: core/security/ | F328: detecteert ongewenste wijzigingen in bestanden of logs | G328: Nog niet gebouwd | H328: =IF(COUNTIFS(D:D,D328)>1,"DUBBEL","")
A329: =ROW()-1 -> 328 | B329: 5 | C329: Security Suite | D329: intrusion_logger.py | E329: core/security/ | F329: noteert verdachte aanroepen (failed auth, rate spikes) | G329: Nog niet gebouwd | H329: =IF(COUNTIFS(D:D,D329)>1,"DUBBEL","")
A330: =ROW()-1 -> 329 | B330: 5 | C330: Security Suite | D330: sandbox_guard.py | E330: core/security/ | F330: monitort experimentele modules (lab/AI sandbox) | G330: Nog niet gebouwd | H330: =IF(COUNTIFS(D:D,D330)>1,"DUBBEL","")
A331: =ROW()-1 -> 330 | B331: 5 | C331: Self & Consciousness Suite | D331: self_reflector.py | E331: core/self/ | F331: Laat Jarvis reflecteren op haar acties en beslissingen; logt haar eigen leerervaringen act-level reflecties: kijkt naar beslissingen, fouten of successen, koppelt feedback aan learning_queue & growth_logger | G331: Nog niet gebouwd | H331: =IF(COUNTIFS(D:D,D331)>1,"DUBBEL","")
... A341: =ROW()-1 -> 340 | B341: 6 | C341: Self & Consciousness Suite | D341: core_echo.py | E341: modules/self/ | F341: testmodule die haar “zelfbeeld” terugkaatst naar reasoning_bridge (“ik denk dat ik…”), handig voor metacognitieve experimenten. | G341: Nog niet gebouwd | H341: =IF(COUNTIFS(D:D,D341)>1,"DUBBEL","")
A342: =ROW()-1 -> 341 | B342: 4 → 5 | C342: Social & Posting Suite | D342: social_stealth_guard.py | E342: modules/social/guards/ | F342: Menselijk ritme, formats mix, anti‑spam, ToS‑proof | G342: Nog niet gebouwd | H342: =IF(COUNTIFS(D:D,D342)>1,"DUBBEL","")
A343: =ROW()-1 -> 342 | B343: 4 | C343: Social & Posting Suite | D343: forum_connector.py | E343: modules/social/connectors/ | F343: scrape/API + queries per forum. | G343: Nog niet gebouwd | H343: =IF(COUNTIFS(D:D,D343)>1,"DUBBEL","")
A344: =ROW()-1 -> 343 | B344: 4 → 5 | C344: Social & Posting Suite | D344: x_connector.py | E344: modules/social/connectors/ | F344: 1 adapter voor X; shadow-read in F4. | G344: Nog niet gebouwd | H344: =IF(COUNTIFS(D:D,D344)>1,"DUBBEL","")
A345: =ROW()-1 -> 344 | B345: 5 | C345: Social & Posting Suite | D345: reply_orchestrator.py | E345: modules/social/posting/ | F345: toon/intent-gevoelige replies. | G345: Nog niet gebouwd | H345: =IF(COUNTIFS(D:D,D345)>1,"DUBBEL","")
...

Sheet Models & LLMs
A1: # | B1: Model name | C1: Type | D1: Size | E1: Quantization | F1: Status | G1: Device | H1: Notes
A2: =ROW()-1 -> 1 | B2: Chat 7B (Nous-Capybara-7B) | C2: LLM | D2: 7B | E2: GGUF Q5_0 | G2: Laptop/Unraid | H2: Puberchat default; snel & speels
A3: =ROW()-1 -> 2 | B3: Think 14B (Qwen2.5-14B-Instruct) | C3: LLM | D3: 14B | E3: GGUF Q4_K_M | G3: Unraid | H3: Diepe redeneringen/planning (on-demand)
A4: =ROW()-1 -> 3 | B4: Embeddings (bge-m3) | C4: Embedder | D4: -- | E4: FP16 / INT8 | G4: Pi worker | H4: Vector search voor geheugen
A5: =ROW()-1 -> 4 | B5: Reranker (bge-reranker-base-v2) | C5: Reranker | D5: -- | E5: FP16 | G5: Pi worker | H5: Betere rangschikking van context
A6: =ROW()-1 -> 5 | B6: Coder Qwen 7B (Qwen2.5-Coder-7B) | C6: LLM | D6: 7B | E6: GGUF Q5_0 | G6: Unraid | H6: Alternatieve coder (meer uitleg)
A7: =ROW()-1 -> 6 | B7: Phi-3 Mini (Phi-3-mini-4k) | C7: LLM | D7: 3.8B | E7: GGUF Q5_0 | G7: Laptop/Pi | H7: Snelle codehulp & snappy antwoorden; laag verbruik
A8: =ROW()-1 -> 7 | B8: Vision 7B (LLaVA-1.6-Mistral-7B of Qwen-VL-7B) | C8: VLM | D8: 7B | E8: GGUF Q4_K_M | G8: Unraid (GPU) | H8: Screenshots/GUI/vision
A9: =ROW()-1 -> 8 | B9: Piano Model (ONNX/MIDI) | C9: Audio/Music | D9: -- | E9: ONNX | G9: Laptop/Unraid | H9: Pitch/notes detectie; lage latency nodig

Sheet CountsPerSuite
A1: Suite | B1: Count
A2: Automotive & Mobility | B2: =COUNTIFS(Inventory!C:C, A2) -> 6
A3: Autonomy & Drive | B3: =COUNTIFS(Inventory!C:C, A3) -> 5 | G3: Actief | H3: Niet Actief | I3: Nog niet gebouwd | J3: Skeleton
A4: Bias & Fairness | B4: =COUNTIFS(Inventory!C:C, A4) -> 5 | G4: =COUNTIFS(Inventory!G:G, G3) -> 0 | H4: =COUNTIFS(Inventory!G:G, H3) -> 0 | I4: =COUNTIFS(Inventory!G:G, I3) -> 445 | J4: =COUNTIFS(Inventory!G:G, J3) -> 0
A5: Body & Visual | B5: =COUNTIFS(Inventory!C:C, A5) -> 9
A6: Cloud Fallback | B6: =COUNTIFS(Inventory!C:C, A6) -> 5
A7: Core & Engines | B7: =COUNTIFS(Inventory!C:C, A7) -> 12
A8: Core Reflexes | B8: =COUNTIFS(Inventory!C:C, A8) -> 5
A9: Creative & Fun | B9: =COUNTIFS(Inventory!C:C, A9) -> 3
A10: Defense & Security Suite | B10: =COUNTIFS(Inventory!C:C, A10) -> 14 | M10: FASES
A11: Device Bridges / Scheduler | B11: =COUNTIFS(Inventory!C:C, A11) -> 12 | M11: 2
A12: Devtools/Integration | B12: =COUNTIFS(Inventory!C:C, A12) -> 1 | M12: =COUNTIFS(Inventory!B:B, M11) -> 17
A13: Earnings & Content Suite | B13: =COUNTIFS(Inventory!C:C, A13) -> 7 | M13: Fase 2 → 3
A14: Emotion & Mood Suite | B14: =COUNTIFS(Inventory!C:C, A14) -> 16 | M14: =COUNTIFS(Inventory!B:B, M13) -> 0
A15: Empathy & Relationship Suite | B15: =COUNTIFS(Inventory!C:C, A15) -> 2 | M15: 3 | N15: Ecosystem infra
A16: Environment & Senses Suite | B16: =COUNTIFS(Inventory!C:C, A16) -> 3 | M16: =COUNTIFS(Inventory!B:B, M15) -> 37
A17: Ethics & Trust Suite | B17: =COUNTIFS(Inventory!C:C, A17) -> 2 | M17: Fase 3 → 4
A18: Experimental AI | B18: =COUNTIFS(Inventory!C:C, A18) -> 8 | M18: =COUNTIFS(Inventory!B:B, M17) -> 0
A19: Finance Suite | B19: =COUNTIFS(Inventory!C:C, A19) -> 31 | M19: 4 | N19: GUI & Presence-era foundation
A20: Future Buffs & Brainfarts Suite | B20: =COUNTIFS(Inventory!C:C, A20) -> 2 | M20: =COUNTIFS(Inventory!B:B, M19) -> 192
A21: GUI & Presence Suite | B21: =COUNTIFS(Inventory!C:C, A21) -> 16 | M21: 4 → 5
A22: Icebox/Concept | B22: =COUNTIFS(Inventory!C:C, A22) -> 2 | M22: =COUNTIFS(Inventory!B:B, M21) -> 5
A23: Identity & Access Suite | B23: =COUNTIFS(Inventory!C:C, A23) -> 20 | M23: 5 | N23: Autonomy
A24: Infrastructure | B24: =COUNTIFS(Inventory!C:C, A24) -> 1 | M24: =COUNTIFS(Inventory!B:B, M23) -> 98
A25: Integration Suite | B25: =COUNTIFS(Inventory!C:C, A25) -> 17 | M25: Fase 5 → 6
A26: Learning & Autonomy Suite | B26: =COUNTIFS(Inventory!C:C, A26) -> 18 | M26: =COUNTIFS(Inventory!B:B, M25) -> 0
A27: Learning & Skills | B27: =COUNTIFS(Inventory!C:C, A27) -> 14 | M27: 6
A28: Legal Suite | B28: =COUNTIFS(Inventory!C:C, A28) -> 8 | M28: =COUNTIFS(Inventory!B:B, M27) -> 22
A29: Life & Personality Suite | B29: =COUNTIFS(Inventory!C:C, A29) -> 14
A30: Maker & Repair Suite | B30: =COUNTIFS(Inventory!C:C, A30) -> 8
A31: Memory & Context | B31: =COUNTIFS(Inventory!C:C, A31) -> 16
A32: Models & LLM Suite | B32: =COUNTIFS(Inventory!C:C, A32) -> 7
A33: Observability Suite | B33: =COUNTIFS(Inventory!C:C, A33) -> 4
A34: Offline & Sync Suite | B34: =COUNTIFS(Inventory!C:C, A34) -> 4
A35: Plex & Media Suite | B35: =COUNTIFS(Inventory!C:C, A35) -> 5
A36: Presence Awareness | B36: =COUNTIFS(Inventory!C:C, A36) -> 3
A37: Reasoning & Memory / Planner | B37: =COUNTIFS(Inventory!C:C, A37) -> 1
A38: Reasoning & Planner | B38: =COUNTIFS(Inventory!C:C, A38) -> 2
A39: Recommendation & Review Suite | B39: =COUNTIFS(Inventory!C:C, A39) -> 8
A40: Resource & Ops Suite | B40: =COUNTIFS(Inventory!C:C, A40) -> 5
... A51: World Model | B51: =COUNTIFS(Inventory!C:C, A51) -> 1
B52: =COUNTIFS(Inventory!C:C, A52) -> 0

Sheet Duplicates
A1: Suite | B1: Module | C1: Description
A2: {=_xlfn._xlws.FILTER(Inventory!D2:G820, Inventory!H2:H820="DUBBEL")} -> #VALUE!
